Metadata-Version: 2.1
Name: mysteriumpack
Version: 0.2
Summary: @venaxyt
Home-page: https://github.com/venaxyt/mysterium
Author: Venax
Author-email: venaxumofficial@gmail.com
License: MIT
Keywords: mysteriumpack
Platform: UNKNOWN
Classifier: Development Status :: 5 - Production/Stable
Classifier: Intended Audience :: Education
Classifier: Operating System :: Microsoft :: Windows :: Windows 10
Classifier: License :: OSI Approved :: MIT License
Classifier: Programming Language :: Python :: 3.9
